mercoa/__init__.py
mercoa/bank_lookup/__init__.py
mercoa/bank_lookup/client.py
mercoa/bank_lookup/raw_client.py
mercoa/bank_lookup/types/__init__.py
mercoa/bank_lookup/types/bank_address.py
mercoa/bank_lookup/types/bank_lookup_response.py
mercoa/calculate/__init__.py
mercoa/calculate/client.py
mercoa/calculate/raw_client.py
mercoa/calculate/types/__init__.py
mercoa/calculate/types/calculate_fees_request.py
mercoa/calculate/types/calculate_payment_timing_request.py
mercoa/calculate/types/calculate_payment_timing_response.py
mercoa/calculate/types/estimated_timing.py
mercoa/calculate/types/fee_calculation_type.py
mercoa/calculate/types/invoice_timing.py
mercoa/client.py
mercoa/collection_types/__init__.py
mercoa/collection_types/types/__init__.py
mercoa/collection_types/types/action_base.py
mercoa/collection_types/types/action_id.py
mercoa/collection_types/types/action_response.py
mercoa/collection_types/types/action_status.py
mercoa/collection_types/types/email_collection_action_response.py
mercoa/collection_types/types/email_message_response.py
mercoa/collection_types/types/update_next_action_request.py
mercoa/commons/__init__.py
mercoa/commons/errors/__init__.py
mercoa/commons/errors/bad_request.py
mercoa/commons/errors/conflict.py
mercoa/commons/errors/forbidden.py
mercoa/commons/errors/internal_server_error.py
mercoa/commons/errors/not_found.py
mercoa/commons/errors/unauthorized.py
mercoa/commons/errors/unimplemented.py
mercoa/commons/types/__init__.py
mercoa/commons/types/address.py
mercoa/commons/types/birth_date.py
mercoa/commons/types/bulk_download_format.py
mercoa/commons/types/bulk_download_response.py
mercoa/commons/types/country_code.py
mercoa/commons/types/document_response.py
mercoa/commons/types/document_type.py
mercoa/commons/types/full_name.py
mercoa/commons/types/individual_government_id.py
mercoa/commons/types/order_direction.py
mercoa/commons/types/phone_number.py
mercoa/commons/types/string_or_string_array.py
mercoa/core/__init__.py
mercoa-0.7.2.dist-info/METADATA
mercoa-0.7.2.dist-info/WHEEL
mercoa-0.7.2.dist-info/RECORD
